TiamoTools/__init__.py
TiamoTools/common.py
TiamoTools/dtime.py
TiamoTools/error.py
TiamoTools/log.py
TiamoTools/mongo.py
TiamoTools/mysql.py
TiamoTools/oracle.py
TiamoTools/sql_db_base.py
TiamoTools/xugu.py
TiamoTools/xgcondb/__init__.py
TiamoTools-1.0.3.dist-info/METADATA
TiamoTools-1.0.3.dist-info/WHEEL
TiamoTools-1.0.3.dist-info/top_level.txt
TiamoTools-1.0.3.dist-info/RECORD
