Metadata-Version: 2.1
Name: TiamoTools
Version: 1.0.3
Summary: 简化数据库连接、时间处理及log声明
Home-page: UNKNOWN
Author: wyl
Author-email: <321081840@qq.com>
License: UNKNOWN
Keywords: python,super,tools
Platform: UNKNOWN
Classifier: Intended Audience :: Developers
Classifier: Programming Language :: Python :: 3.8
Requires: PyMySQL
Requires: pymongo
Requires: cx_Oracle
Requires-Python: >=3.8
Requires-Dist: PyMySQL (>=1.0.2)
Requires-Dist: pymongo (>=3.8.0)
Requires-Dist: cx-Oracle (>=8.3.0)
